rdsmproj/__init__.py
rdsmproj/preprocess.py
rdsmproj/query_gard.py
rdsmproj/utils.py
rdsmproj/mapper/__init__.py
rdsmproj/mapper/bin/AbstractMap.py
rdsmproj/mapper/bin/Blacklist.py
rdsmproj/mapper/bin/Map.py
rdsmproj/mapper/bin/RedditMap.py
rdsmproj/mapper/bin/run.py
rdsmproj/sm_reddit/__init__.py
rdsmproj/sm_reddit/convert_subreddit.py
rdsmproj/sm_reddit/get_comment_data.py
rdsmproj/sm_reddit/get_post_data.py
rdsmproj/sm_reddit/zreader.py
rdsmproj/tm_lda/__init__.py
rdsmproj/tm_lda/_ctfidf.py
rdsmproj/tm_lda/lda_model.py
rdsmproj/tm_lda/main_legacy.py
rdsmproj/tm_lda/topic_tools.py
rdsmproj/tm_t2v/__init__.py
rdsmproj/tm_t2v/main_top2vec.py
rdsmproj/tm_t2v/top2vec_model.py
rdsmproj/tm_t2v/top2vec_topic_tools.py
rdsmproj-0.0.1.dist-info/LICENSE
rdsmproj-0.0.1.dist-info/METADATA
rdsmproj-0.0.1.dist-info/WHEEL
rdsmproj-0.0.1.dist-info/top_level.txt
rdsmproj-0.0.1.dist-info/RECORD
