Metadata-Version: 2.1
Name: rdsmproj
Version: 0.0.1
Summary: Set of tools for use in research of rare disease related text.
Author-email: Bradley Karas <bradley.karas@gmail.com>, Devon Leadman <devon.leadman@axleinfo.com>, William Kariampuzha <William.Kariampuzha@axleinfo.com>
License: PUBLIC DOMAIN NOTICE
Project-URL: homepage, https://github.com/ncats/Rare-Disease-Social-Media-Project
Project-URL: documentation, https://github.com/ncats/Rare-Disease-Social-Media-Project
Project-URL: repository, https://github.com/ncats/Rare-Disease-Social-Media-Project
Keywords: Rare diseases,Natural Language Processing,Data Science,Infodemiology,top2vec,NormMap
Classifier: Development Status :: 1 - Planning
Classifier: Programming Language :: Python :: 3
Classifier: Intended Audience :: Science/Research
Classifier: Topic :: Scientific/Engineering :: Artificial Intelligence
Classifier: Topic :: Scientific/Engineering :: Information Analysis
Classifier: Operating System :: OS Independent
Requires-Python: >=3.7
License-File: LICENSE
Requires-Dist: pandas (>=1.4.2)
Provides-Extra: mapper
Requires-Dist: nltk (>=3.6.7) ; extra == 'mapper'
Requires-Dist: spacy (>=3.2.1) ; extra == 'mapper'
Provides-Extra: sm_reddit
Requires-Dist: pmaw (>=2.1.0) ; extra == 'sm_reddit'
Requires-Dist: tqdm (>=4.62.3) ; extra == 'sm_reddit'
Requires-Dist: zstandard (>=0.17.0) ; extra == 'sm_reddit'
Provides-Extra: tm_lda
Requires-Dist: bertopic (>=0.9.4) ; extra == 'tm_lda'
Requires-Dist: contractions ; extra == 'tm_lda'
Requires-Dist: gensim (>=4.1.2) ; extra == 'tm_lda'
Requires-Dist: hyperopt (>=0.2.7) ; extra == 'tm_lda'
Requires-Dist: matplotlib (>=3.5.1) ; extra == 'tm_lda'
Requires-Dist: nltk (>=3.6.5) ; extra == 'tm_lda'
Requires-Dist: numpy (>=1.22.3) ; extra == 'tm_lda'
Requires-Dist: optuna (>=2.10.0) ; extra == 'tm_lda'
Requires-Dist: psutil (>=5.9.0) ; extra == 'tm_lda'
Requires-Dist: scipy (>=1.7.3) ; extra == 'tm_lda'
Requires-Dist: seaborn (>=0.11.2) ; extra == 'tm_lda'
Requires-Dist: scikit-learn (>=1.0) ; extra == 'tm_lda'
Requires-Dist: tqdm (>=4.62.3) ; extra == 'tm_lda'
Requires-Dist: wordcloud (>=1.8.1) ; extra == 'tm_lda'
Provides-Extra: tm_t2v
Requires-Dist: contractions ; extra == 'tm_t2v'
Requires-Dist: gensim (>=4.1.2) ; extra == 'tm_t2v'
Requires-Dist: matplotlib (>=3.5.1) ; extra == 'tm_t2v'
Requires-Dist: nltk (>=3.6.5) ; extra == 'tm_t2v'
Requires-Dist: numpy (>=1.22.3) ; extra == 'tm_t2v'
Requires-Dist: psutil (>=5.9.0) ; extra == 'tm_t2v'
Requires-Dist: seaborn (>=0.11.2) ; extra == 'tm_t2v'
Requires-Dist: top2vec (>=1.0.27) ; extra == 'tm_t2v'
Requires-Dist: tqdm (>=4.62.3) ; extra == 'tm_t2v'
Requires-Dist: wordcloud (>=1.8.1) ; extra == 'tm_t2v'
